[
  {
    "info": "SGP4 (LEO) Test TLE",
    "tle_line_1": "1 88888U          80275.98708465  .00073094  13844-3  66816-4 0    8",
    "tle_line_2": "2 88888  72.8435 115.9689 0086731  52.6988 110.5714 16.05824518  105",
    "results": [
      {
        "time": 0.0,
        "known_pos": [
          2328.97048951,
          -5995.22076416,
          1719.97067261
        ],
        "known_vel": [
          2.91207230,
          -0.98341546,
          -7.09081703
        ]
      },
      {
        "time": 360.0,
        "known_pos": [
          2456.10705566,
          -6071.93853760,
          1222.89727783
        ],
        "known_vel": [
          2.67938992,
          -0.44829041,
          -7.22879231
        ]
      },
      {
        "time": 720.0,
        "known_pos": [
          2567.56195068,
          -6112.50384522,
          713.96397400
        ],
        "known_vel": [
          2.44024599,
          0.09810869,
          -7.31995916
        ]
      },
      {
        "time": 1080.0,
        "known_pos": [
          2663.09078980,
          -6115.48229980,
          196.39640427
        ],
        "known_vel": [
          2.19611958,
          0.65241995,
          -7.36282432
        ]
      },
      {
        "time": 1440.0,
        "known_pos": [
          2742.55133057,
          -6079.67144775,
          -326.38095856
        ],
        "known_vel": [
          1.94850229,
          1.21106251,
          -7.35619372
        ]
      }
    ]
  },
  {
    "info": "SDP4 (Deep Space) Test TLE",
    "tle_line_1": "1 11801U          80230.29629788  .01431103  00000-0  14311-1        ",
    "tle_line_2": "2 11801  46.7916 230.4354 7318036  47.4722  10.4117  2.28537848      ",
    "results": [
      {
        "time": 0.0,
        "known_pos": [
          7473.37066650,
          428.95261765,
          5828.74786377
        ],
        "known_vel": [
          5.10715413,
          6.44468284,
          -0.18613096
        ]
      },
      {
        "time": 360.0,
        "known_pos": [
          -3305.22537232,
          32410.86328125,
          -24697.17675781
        ],
        "known_vel": [
          -1.30113538,
          -1.15131518,
          -0.28333528
        ]
      },
      {
        "time": 720.0,
        "known_pos": [
          14271.28759766,
          24110.46411133,
          -4725.76837158
        ],
        "known_vel": [
          -0.32050445,
          2.67984074,
          -2.08405289
        ]
      },
      {
        "time": 1080.0,
        "known_pos": [
          -9990.05883789,
          22717.35522461,
          -23616.89062501
        ],
        "known_vel": [
          -1.01667246,
          -2.29026759,
          0.72892364
        ]
      },
      {
        "time": 1440.0,
        "known_pos": [
          9787.86975097,
          33753.34667969,
          -15030.81176758
        ],
        "known_vel": [
          -1.09425066,
          0.92358845,
          -1.52230928
        ]
      }
    ]
  }
]
